beast_dream_snow_loader/__init__.py
beast_dream_snow_loader/models/__init__.py
beast_dream_snow_loader/models/servicenow.py
beast_dream_snow_loader/models/unifi.py
beast_dream_snow_loader/operations/__init__.py
beast_dream_snow_loader/operations/circuit_breaker.py
beast_dream_snow_loader/operations/config.py
beast_dream_snow_loader/operations/error_handler.py
beast_dream_snow_loader/operations/health.py
beast_dream_snow_loader/operations/logger.py
beast_dream_snow_loader/operations/metrics.py
beast_dream_snow_loader/operations/retry.py
beast_dream_snow_loader/servicenow/__init__.py
beast_dream_snow_loader/servicenow/api_client.py
beast_dream_snow_loader/servicenow/loader.py
beast_dream_snow_loader/transformers/__init__.py
beast_dream_snow_loader/transformers/schema_mapper.py
beast_dream_snow_loader/transformers/unifi_to_snow.py
beast_dream_snow_loader-0.3.0.dist-info/METADATA
beast_dream_snow_loader-0.3.0.dist-info/WHEEL
beast_dream_snow_loader-0.3.0.dist-info/licenses/LICENSE
beast_dream_snow_loader-0.3.0.dist-info/RECORD
