Metadata-Version: 2.4
Name: beast-dream-snow-loader
Version: 0.3.0
Summary: UniFi Dream Machine → ServiceNow CMDB Data Loader with Operational Resilience
Project-URL: Homepage, https://github.com/nkllon/beast-dream-snow-loader
Project-URL: Repository, https://github.com/nkllon/beast-dream-snow-loader
Project-URL: Documentation, https://github.com/nkllon/beast-dream-snow-loader#readme
Project-URL: Bug Tracker, https://github.com/nkllon/beast-dream-snow-loader/issues
Project-URL: PyPI, https://pypi.org/project/beast-dream-snow-loader/
Author-email: Lou Springer <lou@nkllon.com>
Maintainer-email: Lou Springer <lou@nkllon.com>
License: MIT
License-File: LICENSE
Keywords: beastmaster,cmdb,data-loader,integration,servicenow,unifi
Classifier: Development Status :: 4 - Beta
Classifier: Intended Audience :: Developers
Classifier: Intended Audience :: System Administrators
Classifier: License :: OSI Approved :: MIT License
Classifier: Operating System :: OS Independent
Classifier: Programming Language :: Python :: 3
Classifier: Programming Language :: Python :: 3.10
Classifier: Programming Language :: Python :: 3.11
Classifier: Programming Language :: Python :: 3.12
Classifier: Topic :: Software Development :: Libraries :: Python Modules
Classifier: Topic :: System :: Networking
Classifier: Topic :: System :: Systems Administration
Requires-Python: >=3.10
Requires-Dist: psutil
Requires-Dist: pydantic
Requires-Dist: requests
Provides-Extra: dev
Requires-Dist: black>=23.0.0; extra == 'dev'
Requires-Dist: mypy>=1.5.0; extra == 'dev'
Requires-Dist: pytest-asyncio>=0.21.0; extra == 'dev'
Requires-Dist: pytest-cov>=4.1.0; extra == 'dev'
Requires-Dist: pytest>=7.4.0; extra == 'dev'
Requires-Dist: ruff>=0.1.0; extra == 'dev'
Requires-Dist: types-psutil>=5.9.0; extra == 'dev'
Requires-Dist: types-requests>=2.31.0; extra == 'dev'
